meaningless/__init__.py
meaningless/bible_base_downloader.py
meaningless/bible_base_extractor.py
meaningless/bible_csv_downloader.py
meaningless/bible_csv_extractor.py
meaningless/bible_json_downloader.py
meaningless/bible_json_extractor.py
meaningless/bible_web_extractor.py
meaningless/bible_xml_downloader.py
meaningless/bible_xml_extractor.py
meaningless/bible_yaml_downloader.py
meaningless/bible_yaml_extractor.py
meaningless/utilities/__init__.py
meaningless/utilities/common.py
meaningless/utilities/csv_file_interface.py
meaningless/utilities/exceptions.py
meaningless/utilities/json_file_interface.py
meaningless/utilities/xml_file_interface.py
meaningless/utilities/yaml_file_interface.py
meaningless-1.2.0.dist-info/LICENSE.md
meaningless-1.2.0.dist-info/METADATA
meaningless-1.2.0.dist-info/WHEEL
meaningless-1.2.0.dist-info/top_level.txt
meaningless-1.2.0.dist-info/RECORD
