Metadata-Version: 2.2
Name: meaningless
Version: 1.2.0
Summary: Retrieves, processes and downloads Bible passages from Bible Gateway
Author-email: Daniel Tran <dantran.au@gmail.com>
License: MIT License
Project-URL: Homepage, https://github.com/daniel-tran/meaningless
Project-URL: Documentation, https://daniel-tran.github.io/meaningless
Keywords: bible,yaml,json,xml,csv,biblegateway
Classifier: Development Status :: 5 - Production/Stable
Classifier: Intended Audience :: Religion
Classifier: Intended Audience :: Developers
Classifier: License :: OSI Approved :: MIT License
Classifier: Natural Language :: English
Classifier: Operating System :: Microsoft :: Windows
Classifier: Operating System :: POSIX :: Linux
Classifier: Programming Language :: Python :: 3.10
Classifier: Programming Language :: Python :: 3.11
Classifier: Programming Language :: Python :: 3.12
Classifier: Programming Language :: Python :: 3.13
Classifier: Topic :: Religion
Requires-Python: >=3.10
License-File: LICENSE.md
Requires-Dist: beautifulsoup4>=4.11.2
Requires-Dist: ruamel.yaml>=0.17.21
Requires-Dist: xmltodict>=0.13.0
